cent/__init__.py
cent/client/__init__.py
cent/client/async_client.py
cent/client/session/__init__.py
cent/client/session/aiohttp.py
cent/client/session/base_http.py
cent/client/session/base_http_async.py
cent/client/session/base_http_sync.py
cent/client/session/requests.py
cent/client/sync_client.py
cent/dto.py
cent/exceptions.py
cent/py.typed
cent-5.2.0.dist-info/METADATA
cent-5.2.0.dist-info/WHEEL
cent-5.2.0.dist-info/licenses/LICENSE
cent-5.2.0.dist-info/RECORD
